appscandastissueverifier/AttackReplay.py
appscandastissueverifier/Errors.py
appscandastissueverifier/Logs.py
appscandastissueverifier/RequestValidation.py
appscandastissueverifier/ResponseValidation.py
appscandastissueverifier/Utilities.py
appscandastissueverifier/__about__.py
appscandastissueverifier/__init__.py
appscandastissueverifier-1.0.0.dist-info/METADATA
appscandastissueverifier-1.0.0.dist-info/WHEEL
appscandastissueverifier-1.0.0.dist-info/licenses/HCL License Agreement
appscandastissueverifier-1.0.0.dist-info/RECORD
